{
  "produits": [
    {
      "id_produit": "P001",
      "nom": "iPhone 16 Pro 256Go",
      "categorie": "Electronique",
      "sous_categorie": "Smartphones",
      "marque": "Apple",
      "fournisseur": "Apple MENA",
      "prix_catalogue": 12999.0,
      "origine_pays": "USA",
      "date_creation": "2023-01-01",
      "actif": true
    },
    {
      "id_produit": "P002",
      "nom": "Samsung Galaxy S24",
      "categorie": "Electronique",
      "sous_categorie": "Smartphones",
      "marque": "Samsung",
      "fournisseur": "Samsung MA",
      "prix_catalogue": 9499.0,
      "origine_pays": "Corée",
      "date_creation": "2023-01-01",
      "actif": true
    },
    {
      "id_produit": "P003",
      "nom": "Laptop Dell XPS 15",
      "categorie": "electronique",
      "sous_categorie": "Ordinateurs",
      "marque": "Dell",
      "fournisseur": "Dell MENA",
      "prix_catalogue": 14500.0,
      "origine_pays": "USA",
      "date_creation": "2023-01-01",
      "actif": true
    },
    {
      "id_produit": "P004",
      "nom": "Ecouteurs Sony WH-1000",
      "categorie": "ELECTRONIQUE",
      "sous_categorie": "Audio",
      "marque": "Sony",
      "fournisseur": "Sony MA",
      "prix_catalogue": 2799.0,
      "origine_pays": "Japon",
      "date_creation": "2023-01-01",
      "actif": true
    },
    {
      "id_produit": "P005",
      "nom": "Montre Casio G-Shock",
      "categorie": "Mode",
      "sous_categorie": "Montres",
      "marque": "Casio",
      "fournisseur": "Casio MA",
      "prix_catalogue": 1299.0,
      "origine_pays": "Japon",
      "date_creation": "2023-01-01",
      "actif": true
    },
    {
      "id_produit": "P006",
      "nom": "Huile d'olive Maasra",
      "categorie": "Alimentation",
      "sous_categorie": "Huiles",
      "marque": "Maasra",
      "fournisseur": "Coop Tanger",
      "prix_catalogue": 89.0,
      "origine_pays": "Maroc",
      "date_creation": "2023-01-01",
      "actif": true
    },
    {
      "id_produit": "P007",
      "nom": "Couscous Ain Ifrane 1kg",
      "categorie": "Alimentation",
      "sous_categorie": "Cereales",
      "marque": "Ain Ifrane",
      "fournisseur": "Ain Ifrane SA",
      "prix_catalogue": 35.0,
      "origine_pays": "Maroc",
      "date_creation": "2023-01-01",
      "actif": true
    },
    {
      "id_produit": "P008",
      "nom": "T-shirt Zara Homme",
      "categorie": "Mode",
      "sous_categorie": "Vetements",
      "marque": "Zara",
      "fournisseur": "Inditex MA",
      "prix_catalogue": 299.0,
      "origine_pays": "Espagne",
      "date_creation": "2023-01-01",
      "actif": true
    },
    {
      "id_produit": "P009",
      "nom": "Chaussures Nike Air Max",
      "categorie": "Mode",
      "sous_categorie": "Chaussures",
      "marque": "Nike",
      "fournisseur": "Nike MENA",
      "prix_catalogue": 1499.0,
      "origine_pays": "USA",
      "date_creation": "2023-01-01",
      "actif": true
    },
    {
      "id_produit": "P010",
      "nom": "Tablet iPad Air",
      "categorie": "Electronique",
      "sous_categorie": "Tablettes",
      "marque": "Apple",
      "fournisseur": "Apple MENA",
      "prix_catalogue": 7999.0,
      "origine_pays": "USA",
      "date_creation": "2023-01-01",
      "actif": true
    },
    {
      "id_produit": "P011",
      "nom": "Cafetiere Nespresso",
      "categorie": "Electronique",
      "sous_categorie": "Electromenager",
      "marque": "Nespresso",
      "fournisseur": "Nestle MA",
      "prix_catalogue": null,
      "origine_pays": "Suisse",
      "date_creation": "2023-01-01",
      "actif": false
    },
    {
      "id_produit": "P012",
      "nom": "Huile d'argan bio",
      "categorie": "Alimentation",
      "sous_categorie": "Huiles",
      "marque": "Zine",
      "fournisseur": "Coop Agadir",
      "prix_catalogue": 250.0,
      "origine_pays": "Maroc",
      "date_creation": "2023-01-01",
      "actif": true
    },
    {
      "id_produit": "P013",
      "nom": "Robe Kaftan Fassi",
      "categorie": "Mode",
      "sous_categorie": "Vetements",
      "marque": "Artisanat",
      "fournisseur": "Artisans Fes",
      "prix_catalogue": 899.0,
      "origine_pays": "Maroc",
      "date_creation": "2023-01-01",
      "actif": true
    },
    {
      "id_produit": "P014",
      "nom": "Dates Medjool 500g",
      "categorie": "Alimentation",
      "sous_categorie": "Fruits Secs",
      "marque": "Medfouna",
      "fournisseur": "Coop Draa",
      "prix_catalogue": 199.0,
      "origine_pays": "Maroc",
      "date_creation": "2023-01-01",
      "actif": true
    },
    {
      "id_produit": "P015",
      "nom": "Xiaomi Redmi Note 13",
      "categorie": "Electronique",
      "sous_categorie": "Smartphones",
      "marque": "Xiaomi",
      "fournisseur": "Xiaomi MA",
      "prix_catalogue": 3499.0,
      "origine_pays": "Chine",
      "date_creation": "2023-01-01",
      "actif": true
    }
  ]
}